binance_dex/__init__.py
binance_dex/api.py
binance_dex/crypto.py
binance_dex/node_rpc.py
binance_dex/sockets.py
binance_dex/transaction.py
binance_dex/lib/__init__.py
binance_dex/lib/bech32.py
binance_dex/lib/common.py
binance_dex/lib/crypto.py
binance_dex/lib/sockets.py
binance_dex-0.1.3.dist-info/LICENSE
binance_dex-0.1.3.dist-info/METADATA
binance_dex-0.1.3.dist-info/WHEEL
binance_dex-0.1.3.dist-info/top_level.txt
binance_dex-0.1.3.dist-info/RECORD
