Metadata-Version: 2.1
Name: binance-dex
Version: 0.1.3
Summary: Python Library for Binance DEX, including API, Websocket, JSONRPC and Crypto
Home-page: https://github.com/wally-yu/binance-dex
Author: Wally Yu
License: MIT License
Platform: UNKNOWN
